uart_asic/rtl/uart_tx.v
module uart_tx #(
    parameter CLKS_PER_BIT = 434
)(
    input clk,
    input reset,
    input start,
    input [7:0] data_in,
    output reg tx,
    output reg busy,
    output reg tx_done
);

// FSM states
localparam IDLE  = 2'b00;
localparam START = 2'b01;
localparam DATA  = 2'b10;
localparam STOP  = 2'b11;

reg [1:0] state;
reg [15:0] clk_count;
reg [2:0] bit_index;
reg [7:0] shift_reg;

// Edge detector
reg start_prev;
wire start_pulse;

assign start_pulse = start & ~start_prev;

always @(posedge clk or posedge reset) begin
    if (reset)
        start_prev <= 0;
    else
        start_prev <= start;
end

//------------------------------------------------
// UART FSM
//------------------------------------------------
always @(posedge clk or posedge reset) begin

    if (reset) begin
        state <= IDLE;
        tx <= 1'b1;
        busy <= 0;
        tx_done <= 0;
        clk_count <= 0;
        bit_index <= 0;
        shift_reg <= 0;
    end

    else begin

        // default
        tx_done <= 0;

        case(state)

        //------------------------------------------------
        IDLE: begin
            tx <= 1'b1;
            busy <= 0;
            clk_count <= 0;
            bit_index <= 0;

            if (start_pulse) begin
                busy <= 1;
                shift_reg <= data_in;
                state <= START;
            end
        end

        //------------------------------------------------
        START: begin
            tx <= 0;

            if (clk_count < CLKS_PER_BIT-1)
                clk_count <= clk_count + 1;
            else begin
                clk_count <= 0;
                state <= DATA;
            end
        end

        //------------------------------------------------
        DATA: begin
            tx <= shift_reg[0];

            if (clk_count < CLKS_PER_BIT-1)
                clk_count <= clk_count + 1;

            else begin
                clk_count <= 0;
                shift_reg <= shift_reg >> 1;

                if (bit_index < 7)
                    bit_index <= bit_index + 1;
                else begin
                    bit_index <= 0;
                    state <= STOP;
                end
            end
        end

        //------------------------------------------------
        STOP: begin
            tx <= 1'b1;

            if (clk_count < CLKS_PER_BIT-1)
                clk_count <= clk_count + 1;

            else begin
                clk_count <= 0;
                state <= IDLE;
                tx_done <= 1;   // transmission finished
            end
        end

        default: state <= IDLE;

        endcase

    end
end

endmodule

uart_asic/rtl/tb_uart_tx.v
`timescale 1ns/1ps

module tb_uart_tx;

reg clk;
reg reset;
reg start;
reg [7:0] data_in;

wire tx;
wire busy;
wire tx_done;

uart_tx #(
    .CLKS_PER_BIT(8)
) uut (
    .clk(clk),
    .reset(reset),
    .start(start),
    .data_in(data_in),
    .tx(tx),
    .busy(busy),
    .tx_done(tx_done)
);

// Clock
always #5 clk = ~clk;

initial begin

    clk = 0;
    reset = 1;
    start = 0;
    data_in = 0;

    #20
    reset = 0;

    // Send byte
    #20
    data_in = 8'h53;
    start = 1;

    #100
    start = 0;

    // Wait
    #2000

    // Send another byte
    data_in = 8'hA5;
    start = 1;

    #10
    start = 0;

    #2000
    $finish;

end

initial begin
    $dumpfile("uart_tx.vcd");
    $dumpvars(0, tb_uart_tx);
end

endmodule

uart_asic/rtl/uart_tx.vcd
$date
	Fri Mar  6 12:32:54 2026
$end
$version
	Icarus Verilog
$end
$timescale
	1ps
$end
$scope module tb_uart_tx $end
$var wire 1 ! tx_done $end
$var wire 1 " tx $end
$var wire 1 # busy $end
$var reg 1 $ clk $end
$var reg 8 % data_in [7:0] $end
$var reg 1 & reset $end
$var reg 1 ' start $end
$scope module uut $end
$var wire 1 $ clk $end
$var wire 8 ( data_in [7:0] $end
$var wire 1 & reset $end
$var wire 1 ' start $end
$var wire 1 ) start_pulse $end
$var parameter 32 * CLKS_PER_BIT $end
$var parameter 2 + DATA $end
$var parameter 2 , IDLE $end
$var parameter 2 - START $end
$var parameter 2 . STOP $end
$var reg 3 / bit_index [2:0] $end
$var reg 1 # busy $end
$var reg 16 0 clk_count [15:0] $end
$var reg 8 1 shift_reg [7:0] $end
$var reg 1 2 start_prev $end
$var reg 2 3 state [1:0] $end
$var reg 1 " tx $end
$var reg 1 ! tx_done $end
$upscope $end
$upscope $end
$enddefinitions $end
$comment Show the parameter values. $end
$dumpall
b11 .
b1 -
b0 ,
b10 +
b1000 *
$end
#0
$dumpvars
b0 3
02
b0 1
b0 0
b0 /
0)
b0 (
0'
1&
b0 %
0$
0#
1"
0!
$end
#5000
1$
#10000
0$
#15000
1$
#20000
0$
0&
#25000
1$
#30000
0$
#35000
1$
#40000
1)
0$
1'
b1010011 %
b1010011 (
#45000
0)
b1 3
b1010011 1
1#
12
1$
#50000
0$
#55000
b1 0
0"
1$
#60000
0$
#65000
b10 0
1$
#70000
0$
#75000
b11 0
1$
#80000
0$
#85000
b100 0
1$
#90000
0$
#95000
b101 0
1$
#100000
0$
#105000
b110 0
1$
#110000
0$
#115000
b111 0
1$
#120000
0$
#125000
b10 3
b0 0
1$
#130000
0$
#135000
b1 0
1"
1$
#140000
0$
0'
#145000
b10 0
02
1$
#150000
0$
#155000
b11 0
1$
#160000
0$
#165000
b100 0
1$
#170000
0$
#175000
b101 0
1$
#180000
0$
#185000
b110 0
1$
#190000
0$
#195000
b111 0
1$
#200000
0$
#205000
b1 /
b101001 1
b0 0
1$
#210000
0$
#215000
b1 0
1$
#220000
0$
#225000
b10 0
1$
#230000
0$
#235000
b11 0
1$
#240000
0$
#245000
b100 0
1$
#250000
0$
#255000
b101 0
1$
#260000
0$
#265000
b110 0
1$
#270000
0$
#275000
b111 0
1$
#280000
0$
#285000
b10 /
b10100 1
b0 0
1$
#290000
0$
#295000
b1 0
0"
1$
#300000
0$
#305000
b10 0
1$
#310000
0$
#315000
b11 0
1$
#320000
0$
#325000
b100 0
1$
#330000
0$
#335000
b101 0
1$
#340000
0$
#345000
b110 0
1$
#350000
0$
#355000
b111 0
1$
#360000
0$
#365000
b11 /
b1010 1
b0 0
1$
#370000
0$
#375000
b1 0
1$
#380000
0$
#385000
b10 0
1$
#390000
0$
#395000
b11 0
1$
#400000
0$
#405000
b100 0
1$
#410000
0$
#415000
b101 0
1$
#420000
0$
#425000
b110 0
1$
#430000
0$
#435000
b111 0
1$
#440000
0$
#445000
b100 /
b101 1
b0 0
1$
#450000
0$
#455000
b1 0
1"
1$
#460000
0$
#465000
b10 0
1$
#470000
0$
#475000
b11 0
1$
#480000
0$
#485000
b100 0
1$
#490000
0$
#495000
b101 0
1$
#500000
0$
#505000
b110 0
1$
#510000
0$
#515000
b111 0
1$
#520000
0$
#525000
b101 /
b10 1
b0 0
1$
#530000
0$
#535000
b1 0
0"
1$
#540000
0$
#545000
b10 0
1$
#550000
0$
#555000
b11 0
1$
#560000
0$
#565000
b100 0
1$
#570000
0$
#575000
b101 0
1$
#580000
0$
#585000
b110 0
1$
#590000
0$
#595000
b111 0
1$
#600000
0$
#605000
b110 /
b1 1
b0 0
1$
#610000
0$
#615000
b1 0
1"
1$
#620000
0$
#625000
b10 0
1$
#630000
0$
#635000
b11 0
1$
#640000
0$
#645000
b100 0
1$
#650000
0$
#655000
b101 0
1$
#660000
0$
#665000
b110 0
1$
#670000
0$
#675000
b111 0
1$
#680000
0$
#685000
b111 /
b0 1
b0 0
1$
#690000
0$
#695000
b1 0
0"
1$
#700000
0$
#705000
b10 0
1$
#710000
0$
#715000
b11 0
1$
#720000
0$
#725000
b100 0
1$
#730000
0$
#735000
b101 0
1$
#740000
0$
#745000
b110 0
1$
#750000
0$
#755000
b111 0
1$
#760000
0$
#765000
b11 3
b0 /
b0 0
1$
#770000
0$
#775000
b1 0
1"
1$
#780000
0$
#785000
b10 0
1$
#790000
0$
#795000
b11 0
1$
#800000
0$
#805000
b100 0
1$
#810000
0$
#815000
b101 0
1$
#820000
0$
#825000
b110 0
1$
#830000
0$
#835000
b111 0
1$
#840000
0$
#845000
1!
b0 3
b0 0
1$
#850000
0$
#855000
0#
0!
1$
